# Python - Classes and Objects

The objectives of this project are:
```
Why Python programming is awesome
What is OOP
“first-class everything”
What is a class
What is an object and an instance
What is the difference between a class and an object or instance
What is an attribute
What are and how to use public, protected and private attributes
What is self
What is a method
What is the special __init__ method and how to use it
What is Data Abstraction, Data Encapsulation, and Information Hiding
What is a property
What is the difference between an attribute and a property in Python
What is the Pythonic way to write getters and setters in Python
How to dynamically create arbitrary new attributes for existing instances of a class
How to bind attributes to object and classes
What is the __dict__ of a class and/or instance of a class and what does it contain
How does Python find the attributes of an object or class
How to use the getattr function
```

| No | Task | Description |
| :---: | :---: | :---: |
| 0 | [0-square.py](./0-square.py) | My first square |
| 1 | [1-square.py](./1-square.py) | Square with size |
| 2 | [2-square.py](./2-square.py) | Size validation |
| 3 | [3-square.py](./3-square.py) | Area of a square |
| 4 | [4-square.py](./4-square.py) | Access and update private attribute |
| 5 | [5-square.py](./5-square.py) | Printing a square |
| 6 | [6-square.py](./6-square.py) | Coordinates of a square |
| 7 | [100-singly_linked_list.py](./100-singly_linked_list.py) | Singly linked list |
| 8 | [101-square.py](./101-square.py) | Print Square instance |
| 9 | [102-square.py](./102-square.py) | Compare 2 squares |
| 10| [103-magic_class.py](./103-magic_class.py) | ByteCode -> Python #5 |

- **Bytecode**
```
Disassembly of __init__:
 10           0 LOAD_CONST               1 (0)
              3 LOAD_FAST                0 (self)
              6 STORE_ATTR               0 (_MagicClass__radius)

 11           9 LOAD_GLOBAL              1 (type)
             12 LOAD_FAST                1 (radius)
             15 CALL_FUNCTION            1 (1 positional, 0 keyword pair)
             18 LOAD_GLOBAL              2 (int)
             21 COMPARE_OP               9 (is not)
             24 POP_JUMP_IF_FALSE       60
             27 LOAD_GLOBAL              1 (type)
             30 LOAD_FAST                1 (radius)
             33 CALL_FUNCTION            1 (1 positional, 0 keyword pair)
             36 LOAD_GLOBAL              3 (float)
             39 COMPARE_OP               9 (is not)
             42 POP_JUMP_IF_FALSE       60

 12          45 LOAD_GLOBAL              4 (TypeError)
             48 LOAD_CONST               2 ('radius must be a number')
             51 CALL_FUNCTION            1 (1 positional, 0 keyword pair)
             54 RAISE_VARARGS            1
             57 JUMP_FORWARD             0 (to 60)

 13     >>   60 LOAD_FAST                1 (radius)
             63 LOAD_FAST                0 (self)
             66 STORE_ATTR               0 (_MagicClass__radius)
             69 LOAD_CONST               3 (None)
             72 RETURN_VALUE

Disassembly of area:
 17           0 LOAD_FAST                0 (self)
              3 LOAD_ATTR                0 (_MagicClass__radius)
              6 LOAD_CONST               1 (2)
              9 BINARY_POWER
             10 LOAD_GLOBAL              1 (math)
             13 LOAD_ATTR                2 (pi)
             16 BINARY_MULTIPLY
             17 RETURN_VALUE

Disassembly of circumference:
 21           0 LOAD_CONST               1 (2)
              3 LOAD_GLOBAL              0 (math)
              6 LOAD_ATTR                1 (pi)
              9 BINARY_MULTIPLY
             10 LOAD_FAST                0 (self)
             13 LOAD_ATTR                2 (_MagicClass__radius)
             16 BINARY_MULTIPLY
             17 RETURN_VALUE
```
